LICENSE.txt
MANIFEST.in
README.rst
bootstrap.py
buildout.cfg
setup.py
versions.cfg
etc/zuora.cfg
tests/__init__.py
tests/test_scenario.py
wsdls/zuora.a.52.0.wsdl
zuora/__init__.py
zuora/client.py
zuora/transport.py
zuora_client.egg-info/PKG-INFO
zuora_client.egg-info/SOURCES.txt
zuora_client.egg-info/dependency_links.txt
zuora_client.egg-info/not-zip-safe
zuora_client.egg-info/requires.txt
zuora_client.egg-info/top_level.txt